m3/__init__.py
m3/ice.py
m3/ice_simulator.py
m3/m3_common.py
m3/m3_gdb.py
m3/m3_ice.py
m3/m3_logging.py
m3/m3_mbus.py
m3-0.6.10.dist-info/DESCRIPTION.rst
m3-0.6.10.dist-info/METADATA
m3-0.6.10.dist-info/RECORD
m3-0.6.10.dist-info/WHEEL
m3-0.6.10.dist-info/entry_points.txt
m3-0.6.10.dist-info/metadata.json
m3-0.6.10.dist-info/top_level.txt
