Metadata-Version: 2.0
Name: m3
Version: 0.6.10
Summary: Support tools for chips from the M3 ecosystem
Home-page: https://github.com/mbus/m3-python
Author: Pat Pannuto
Author-email: pat.pannuto@gmail.com
License: UNKNOWN
Platform: UNKNOWN
Classifier: Development Status :: 3 - Alpha
Classifier: Environment :: Console
Classifier: Intended Audience :: Developers
Classifier: Intended Audience :: End Users/Desktop
Classifier: License :: OSI Approved :: MIT License
Classifier: Natural Language :: English
Classifier: Operating System :: OS Independent
Classifier: Programming Language :: Python
Classifier: Programming Language :: Python :: 2
Classifier: Programming Language :: Python :: 2.7
Classifier: Topic :: Software Development :: Embedded Systems
Requires-Dist: future
Requires-Dist: nose
Requires-Dist: pyserial
